{
    "i0": "126",
    "Km": "0.5",
    "gears_n": "5",
    "i_avr": "2.63",
    "YF_gear1": "0.019",
    "YF_wheel1": "0.019",
    "gear.yf.1": "3.9",
    "wheel.yf.1": "3.7",
    "gear./.1": "0.019",
    "wheel./.1": "0.025",
    "YF_choose1": "колесу",
    "sigma1": "146.71",
    "yf.1": "5.65",
    "z.1": "38",
    "gear.1.minm": "0.12",
    "m1": "0.2",
    "YF_gear2": "0.019",
    "YF_wheel2": "0.019",
    "gear.yf.2": "3.9",
    "wheel.yf.2": "3.7",
    "gear./.2": "0.019",
    "wheel./.2": "0.025",
    "YF_choose2": "колесу",
    "sigma2": "146.71",
    "yf.2": "5.65",
    "z.2": "38",
    "gear.2.minm": "0.14",
    "m2": "0.2",
    "YF_gear3": "0.019",
    "YF_wheel3": "0.019",
    "gear.yf.3": "3.9",
    "wheel.yf.3": "3.57",
    "gear./.3": "0.019",
    "wheel./.3": "0.024",
    "YF_choose3": "колесу",
    "sigma3": "146.71",
    "yf.3": "5.67",
    "z.3": "71",
    "gear.3.minm": "0.17",
    "m3": "0.2",
    "YF_gear4": "0.019",
    "YF_wheel4": "0.019",
    "gear.yf.4": "3.9",
    "wheel.yf.4": "3.6",
    "gear./.4": "0.019",
    "wheel./.4": "0.025",
    "YF_choose4": "колесу",
    "sigma4": "146.71",
    "yf.4": "5.67",
    "z.4": "106",
    "gear.4.minm": "0.25",
    "m4": "0.3",
    "YF_gear5": "0.018",
    "YF_wheel5": "0.018",
    "gear.yf.5": "3.72",
    "wheel.yf.5": "3.6",
    "gear./.5": "0.018",
    "wheel./.5": "0.025",
    "YF_choose5": "колесу",
    "sigma5": "146.71",
    "yf.5": "5.67",
    "z.5": "160",
    "gear.5.minm": "0.38",
    "m5": "0.4",
    "deltaI": "0.019",
    "kpd.5.F": "11.25",
    "kpd.5.c": "1.24",
    "kpd.5.kpd": "0.97",
    "kpd.5.newM": "124.27",
    "kpd.4.F": "4.69",
    "kpd.4.c": "1.56",
    "kpd.4.kpd": "0.95",
    "kpd.4.newM": "31.4",
    "kpd.3.F": "1.77",
    "kpd.3.c": "2.39",
    "kpd.3.kpd": "0.91",
    "kpd.3.newM": "13.41",
    "kpd.2.F": "1.76",
    "kpd.2.c": "2.4",
    "kpd.2.kpd": "0.89",
    "kpd.2.newM": "9.51",
    "kpd.1.F": "1.25",
    "kpd.1.c": "2.9",
    "kpd.1.kpd": "0.86",
    "kpd.1.newM": "7.44",
    "cs.1.aw": "12.6",
    "cs.1.sigma_n": "34.091",
    "cs.2.aw": "12.6",
    "cs.2.sigma_n": "38.31",
    "cs.3.aw": "24",
    "cs.3.sigma_n": "21.46",
    "cs.4.aw": "32.75",
    "cs.4.sigma_n": "25.93",
    "cs.5.aw": "58.8",
    "cs.5.sigma_n": "26.63",
    "loft.phi": "0.16",
    "loft.A1": "34.23",
    "loft.P2": "15.78",
    "loft.P3": "16.61",
    "loft.L1": "22.44",
    "loft.F2": "5.44",
    "loft.z": "2.9",
    "loft.n": "26",
    "loft.n1": "26",
    "loft.H0": "12.15",
    "loft.L_dash": "16.55",
    "shaft.M": "124.27",
    "shaft.F_circ1": "4.69",
    "shaft.F_circ2": "11.51",
    "shaft.F_r1": "1.71",
    "shaft.F_r2": "4.19",
    "shaft.R_B_x": "7.43",
    "shaft.R_B_y": "1.95",
    "shaft.R_A_x": "8.76",
    "shaft.R_A_y": "0.53",
    "shaft.Mkx": "91.36",
    "shaft.Mky": "24.3",
    "shaft.Msum_izg": "94.54",
    "shaft.M_pr": "143.25",
    "shaft.d_min": "2.43",
    "shaft.d_min_round": "3",
    "shaft.P": "10.53",
    "shaft.F_R": "8.78",
    "shaft.F_r_A": "8.78",
    "shaft.F_r_B": "7.69",
    "shaft.n": "218",
    "shaft.Cp": "35.79",
    "M_load": "540",
    "N_min": "3.71",
    "engine.name": "ДГ-5ТА",
    "engine.N": "5",
    "engine.n": "6000",
    "engine.Mn": "10",
    "engine.Mstart": "22",
    "engine.Jr": "4E-7",
    "engine.D": "61",
    "engine.L": "142",
    "engine.U": "36",
    "realI": "123.65",
    "momE": "10",
    "momN": "7.0073",
    "i0-1": "1.51",
    "i1-2": "1.62",
    "i2-3": "2.63",
    "i3-4": "4.27",
    "i4-5": "4.57",
    "M0": "5",
    "M1": "7.33",
    "M2": "11.52",
    "M3": "29.4",
    "M4": "121.79",
    "M5": "540",
    "gears.1.d": "10",
    "gears.1.da": "10.8",
    "gears.1.df": "8.8",
    "gears.1.z": "25",
    "gears.2.d": "15.2",
    "gears.2.da": "16",
    "gears.2.df": "14",
    "gears.2.z": "38",
    "gears.1.b": "3.2",
    "gears.1.a": "12.6",
    "gears.1.i": "1.51",
    "gears.1.m": "0.4",
    "gears.3.d": "10",
    "gears.3.da": "10.8",
    "gears.3.df": "8.8",
    "gears.3.z": "25",
    "gears.4.d": "15.2",
    "gears.4.da": "16",
    "gears.4.df": "14",
    "gears.4.z": "38",
    "gears.3.b": "3.2",
    "gears.3.a": "12.6",
    "gears.3.i": "1.62",
    "gears.3.m": "0.4",
    "gears.5.d": "12.5",
    "gears.5.da": "13.5",
    "gears.5.df": "11",
    "gears.5.z": "25",
    "gears.6.d": "35.5",
    "gears.6.da": "36.5",
    "gears.6.df": "34",
    "gears.6.z": "71",
    "gears.5.b": "4",
    "gears.5.a": "24",
    "gears.5.i": "2.63",
    "gears.5.m": "0.5",
    "gears.7.d": "12.5",
    "gears.7.da": "13.5",
    "gears.7.df": "11",
    "gears.7.z": "25",
    "gears.8.d": "53",
    "gears.8.da": "54",
    "gears.8.df": "51.5",
    "gears.8.z": "106",
    "gears.7.b": "4",
    "gears.7.a": "32.75",
    "gears.7.i": "4.27",
    "gears.7.m": "0.5",
    "gears.9.d": "21.6",
    "gears.9.da": "22.8",
    "gears.9.df": "19.98",
    "gears.9.z": "36",
    "gears.10.d": "96",
    "gears.10.da": "97.2",
    "gears.10.df": "94.38",
    "gears.10.z": "160",
    "gears.9.b": "4.8",
    "gears.9.a": "58.8",
    "gears.9.i": "4.57",
    "gears.9.m": "0.6",
    "spr.name": "№173 II класса 2 разряда",
    "spr.P3": "16.67",
    "spr.d": "0.45",
    "spr.D": "2.2",
    "spr.z1": "75.033",
    "spr.f3": "0.22",
    "spr.L": "17",
    "loftwheel.z": "160",
    "loftwheel.m": "0.6",
    "loftwheel.M": "540",
    "loftwheel.spring": "{'name': '№173 II класса 2 разряда', 'P3': 16.6719, 'd': 0.45, 'D': 2.2, 'z1': 75.033357, 'f3': 0.222, 'L': 17}",
    "loftwheel.A": "35",
    "loftwheel.xi": "2",
    "loftwheel.d": "0.05",
    "loftwheel.n": "4",
    "text": "12300",
    "material.w.name": "сталь 45",
    "material.w.sigma_b": "580",
    "material.w.sigma_t": "360",
    "material.w.sigma_1": "249.4",
    "material.w.sigma_f": "146.71",
    "material.w.sigma_H": "428.97",
    "material.g.name": "сталь 40Х",
    "material.g.sigma_b": "1000",
    "material.g.sigma_t": "830",
    "material.g.sigma_1": "350",
    "material.g.sigma_f": "205.88",
    "material.g.sigma_H": "602",
    "material.s.name": "сталь 40Х",
    "material.s.sigma_b": "1000",
    "material.s.sigma_t": "830",
    "material.s.sigma_1": "430",
    "material.s.sigma_f": "0",
    "material.s.sigma_H": "0",
    "podsh.name": "Подшипник шариковый радиальный однорядный №2000083 ГОСТ 8538-74",
    "podsh.d": "3",
    "podsh.D": "7",
    "podsh.B": "2.5",
    "podsh.r": "0.3",
    "podsh.C": "430",
    "podsh.C0": "136",
    "Yb": "8"
}